myfunctions_pinar15/__init__.py
myfunctions_pinar15/math.py
myfunctions_pinar15-0.0.9.dist-info/METADATA
myfunctions_pinar15-0.0.9.dist-info/WHEEL
myfunctions_pinar15-0.0.9.dist-info/top_level.txt
myfunctions_pinar15-0.0.9.dist-info/RECORD
