Metadata-Version: 2.1
Name: myfunctions-pinar15
Version: 0.0.9
Summary: A description of your package
Home-page: https://github.com/pinar15/class4
Author: Pinar Dasdemir
Author-email: pdasdemir49@gmail.com
License: MIT
Platform: UNKNOWN
Classifier: Programming Language :: Python :: 3
Classifier: License :: OSI Approved :: MIT License
Classifier: Operating System :: OS Independent
Requires-Python: >=3.6
